DDCO_Counters/john.v
module johnson_counter(
    Clock,
    Reset,
    Count_out
    );

    //what are the input ports and their sizes.
    input Clock;
    input Reset;
    //what are the output ports and their sizes.
    output [3:0] Count_out;
    //Internal variables
    reg [3:0] Count_temp;

    //Whenever the Clock changes from 0 to 1(positive edge) or 
    //a change in Reset, execute the always block.
    always @(posedge(Clock) or Reset)
    begin
        if(Reset == 1'b1)   begin  //when Reset is high 
            Count_temp = 4'b0000;   end  //The Count value is reset to "0000".
        else if(Clock == 1'b1)  begin  //When the Clock is high
            //Left shift the Count value and at the same time
            //negate the least significant bit.
            Count_temp = {Count_temp[2:0],~Count_temp[3]};  end 
    end
    
    //The Count value is assigned to final output port.
    assign Count_out = Count_temp;
    
endmodule

DDCO_Counters/john_tb.v
module tb_john;

    // Inputs
    reg Clock;
    reg Reset;

    // Outputs
    wire [3:0] Count_out;

    // Instantiate the Unit Under Test (UUT)
    johnson_counter uut (
        .Clock(Clock), 
        .Reset(Reset), 
        .Count_out(Count_out)
    );

    ///////////////////Clock generation ///////////////////////////
    initial Clock = 0; 
    always #10 Clock = ~Clock; 
    ////////// #10 means wait for 10 ns before executing the next statement. ///////////
    
    //Simulation inputs.
    initial begin
    //Apply Reset for 50 ns.
        Reset = 1; //Reset is high
        #10;       //Wait for 50 ns
        Reset = 0; //Reset is low.
        #150 $finish;
    end
    initial begin
          $monitor($time, " clock=%1b,reset=%1b,q=%4b",Clock,Reset,Count_out);
		end
		initial begin $dumpfile("tb_johnsontest.vcd"); $dumpvars(0, tb_john); end
      
endmodule

DDCO_Counters/tb_johnsontest.vcd
$date
	Wed Nov 24 11:56:49 2021
$end
$version
	Icarus Verilog
$end
$timescale
	1s
$end
$scope module tb_john $end
$var wire 4 ! Count_out [3:0] $end
$var reg 1 " Clock $end
$var reg 1 # Reset $end
$scope module uut $end
$var wire 1 $ Clock $end
$var wire 4 % Count_out [3:0] $end
$var wire 1 & Reset $end
$var reg 4 ' Count_temp [3:0] $end
$upscope $end
$upscope $end
$enddefinitions $end
#0
$dumpvars
b0 '
1&
b0 %
0$
1#
0"
b0 !
$end
#10
b1 '
b1 !
b1 %
0#
0&
1"
1$
#20
0"
0$
#30
b11 '
b11 !
b11 %
1"
1$
#40
0"
0$
#50
b111 '
b111 !
b111 %
1"
1$
#60
0"
0$
#70
b1111 '
b1111 !
b1111 %
1"
1$
#80
0"
0$
#90
b1110 '
b1110 !
b1110 %
1"
1$
#100
0"
0$
#110
b1100 '
b1100 !
b1100 %
1"
1$
#120
0"
0$
#130
b1000 '
b1000 !
b1000 %
1"
1$
#140
0"
0$
#150
b0 '
b0 !
b0 %
1"
1$
